libestg3b/__init__.py
libestg3b/countries.py
libestg3b/estg3b.py
libestg3b/matcher.py
libestg3b/rule.py
libestg3b-0.0.5.dist-info/LICENSE
libestg3b-0.0.5.dist-info/METADATA
libestg3b-0.0.5.dist-info/WHEEL
libestg3b-0.0.5.dist-info/top_level.txt
libestg3b-0.0.5.dist-info/zip-safe
libestg3b-0.0.5.dist-info/RECORD
