Metadata-Version: 2.1
Name: libestg3b
Version: 0.0.5
Home-page: https://github.com/uberspace/libestg3b
Author: uberspace.de
Author-email: hallo@uberspace.de
Classifier: Development Status :: 4 - Beta
Classifier: Intended Audience :: Developers
Classifier: Intended Audience :: Information Technology
Classifier: Topic :: Office/Business :: Financial
Classifier: Natural Language :: English
Classifier: Operating System :: POSIX :: Linux
Classifier: Programming Language :: Python :: 3.6
Classifier: Programming Language :: Python :: 3.7
Classifier: License :: OSI Approved :: MIT License
License-File: LICENSE
Requires-Dist: holidays
Requires-Dist: pytz
Requires-Dist: python-dateutil
Requires-Dist: dataclasses
Provides-Extra: dev
Requires-Dist: pylava==0.2.*; extra == "dev"
Requires-Dist: isort==4.3.*; extra == "dev"
Requires-Dist: pytest==3.8.*; extra == "dev"
Requires-Dist: pytest-cov; extra == "dev"
Requires-Dist: tox; extra == "dev"
Requires-Dist: codecov; extra == "dev"
Requires-Dist: twine; extra == "dev"
Requires-Dist: sphinx; extra == "dev"
Requires-Dist: sphinx-autobuild; extra == "dev"
Requires-Dist: sphinx-autodoc-typehints; extra == "dev"
Requires-Dist: sphinx-rtd-theme; extra == "dev"
